turbid/__init__.py
turbid/turbid.py
turbid/ext/sqlalchemy.py
turbid-0.2.2.dist-info/METADATA
turbid-0.2.2.dist-info/WHEEL
turbid-0.2.2.dist-info/licenses/LICENSE
turbid-0.2.2.dist-info/RECORD
