Metadata-Version: 2.4
Name: turbid
Version: 0.2.2
Summary: Transparent obfuscation of numeric IDs
Project-URL: Repository, https://github.com/pjwerneck/turbid
Project-URL: Bug Tracker, https://github.com/pjwerneck/turbid/issues
Author-email: Pedro Werneck <pjwerneck@gmail.com>
License: MIT
License-File: LICENSE
Requires-Python: <4.0,>=3.8
Requires-Dist: fastfpe<1.0.0,>=0.2.0
Provides-Extra: sqlalchemy
Requires-Dist: sqlalchemy<3.0.0,>=1.4.0; extra == 'sqlalchemy'
